MANIFEST.in
README.txt
setup.cfg
setup.py
docs/HISTORY.txt
docs/INSTALL.txt
docs/LICENSE.GPL
docs/LICENSE.txt
zopyx/__init__.py
zopyx.ecardsng.egg-info/PKG-INFO
zopyx.ecardsng.egg-info/SOURCES.txt
zopyx.ecardsng.egg-info/dependency_links.txt
zopyx.ecardsng.egg-info/entry_points.txt
zopyx.ecardsng.egg-info/namespace_packages.txt
zopyx.ecardsng.egg-info/not-zip-safe
zopyx.ecardsng.egg-info/paster_plugins.txt
zopyx.ecardsng.egg-info/requires.txt
zopyx.ecardsng.egg-info/top_level.txt
zopyx/ecardsng/__init__.py
zopyx/ecardsng/config.py
zopyx/ecardsng/configure.zcml
zopyx/ecardsng/interfaces.py
zopyx/ecardsng/skins.zcml
zopyx/ecardsng/tests.py
zopyx/ecardsng/browser/__init__.py
zopyx/ecardsng/browser/configure.zcml
zopyx/ecardsng/content/__init__.py
zopyx/ecardsng/content/configure.zcml
zopyx/ecardsng/content/ecards.py
zopyx/ecardsng/i18n/zopyxecardsng-de.po
zopyx/ecardsng/portlets/__init__.py
zopyx/ecardsng/portlets/configure.zcml
zopyx/ecardsng/profiles/default/factorytool.xml
zopyx/ecardsng/profiles/default/metadata.xml
zopyx/ecardsng/profiles/default/portlets.xml
zopyx/ecardsng/profiles/default/propertiestool.xml
zopyx/ecardsng/profiles/default/skins.xml
zopyx/ecardsng/profiles/default/types.xml
zopyx/ecardsng/profiles/default/workflows.xml
zopyx/ecardsng/profiles/default/types/ECard.xml
zopyx/ecardsng/profiles/default/types/ECardsFolder.xml
zopyx/ecardsng/profiles/default/types/ECardsSavedFolder.xml
zopyx/ecardsng/skins/zopyx_ecardsng/ecard_macros.pt
zopyx/ecardsng/skins/zopyx_ecardsng/ecard_matrix.py
zopyx/ecardsng/skins/zopyx_ecardsng/ecard_selection.cpt
zopyx/ecardsng/skins/zopyx_ecardsng/ecard_selection.cpt.metadata
zopyx/ecardsng/skins/zopyx_ecardsng/ecard_validate.vpy
zopyx/ecardsng/skins/zopyx_ecardsng/ecard_view.pt
zopyx/ecardsng/skins/zopyx_ecardsng/ecardsfolder_view.pt
zopyx/ecardsng/tests/__init__.py
zopyx/ecardsng/tests/doc_tests.py