Metadata-Version: 1.0
Name: zopyx.ecardsng
Version: 0.3.3
Summary: An ECard implementation for Plone
Home-page: http://svn.plone.org/svn/collective/zopyx.ecardsng/trunk
Author: Andreas Jung
Author-email: info@zopyx.com
License: ZPL
Keywords: Plone Zope ECards
Platform: UNKNOWN
Classifier: Framework :: Plone
Classifier: Intended Audience :: Developers
Classifier: Topic :: Software Development :: Libraries :: Python Modules
Classifier: License :: OSI Approved :: Zope Public License
